docs/source/conf.py
examples/mask-detector-workflow/blurry-faces/src/DetectorAPI.py
examples/mask-detector-workflow/blurry-faces/src/auto_blur_image.py
examples/mask-detector-workflow/blurry-faces/src/auto_blur_video.py
examples/mask-detector-workflow/blurry-faces/src/manual_blur_image.py
examples/mask-detector-workflow/mask-detector/mask-detector-image.py
scar/cmdtemplate.py
scar/exceptions.py
scar/logger.py
scar/scarcli.py
scar/utils.py
scar/version.py
scar/http/request.py
scar/parser/cfgfile.py
scar/parser/fdl.py
scar/parser/cli/__init__.py
scar/parser/cli/parents.py
scar/parser/cli/subparsers.py
scar/providers/aws/__init__.py
scar/providers/aws/apigateway.py
scar/providers/aws/batchfunction.py
scar/providers/aws/cloudwatchlogs.py
scar/providers/aws/containerimage.py
scar/providers/aws/controller.py
scar/providers/aws/ecr.py
scar/providers/aws/functioncode.py
scar/providers/aws/iam.py
scar/providers/aws/lambdafunction.py
scar/providers/aws/lambdalayers.py
scar/providers/aws/launchtemplates.py
scar/providers/aws/resourcegroups.py
scar/providers/aws/response.py
scar/providers/aws/s3.py
scar/providers/aws/udocker.py
scar/providers/aws/validators.py
scar/providers/aws/clients/__init__.py
scar/providers/aws/clients/apigateway.py
scar/providers/aws/clients/batchfunction.py
scar/providers/aws/clients/cloudwatchlogs.py
scar/providers/aws/clients/ec2.py
scar/providers/aws/clients/ecr.py
scar/providers/aws/clients/iam.py
scar/providers/aws/clients/lambdafunction.py
scar/providers/aws/clients/resourcegroups.py
scar/providers/aws/clients/s3.py
scar/providers/oscar/client.py
scar/providers/oscar/controller.py
scar/providers/oscar/response.py
test/__init__.py
test/functional/__init__.py
test/functional/aws.py
test/functional/parser/__init__.py
test/functional/parser/fdl.py
test/unit/test_scarcli.py
test/unit/aws/test_apigateway.py
test/unit/aws/test_batch.py
test/unit/aws/test_cloudwatchlogs.py
test/unit/aws/test_controller.py
test/unit/aws/test_ecr.py
scar-4.3.1.dist-info/LICENSE
scar-4.3.1.dist-info/METADATA
scar-4.3.1.dist-info/WHEEL
scar-4.3.1.dist-info/entry_points.txt
scar-4.3.1.dist-info/top_level.txt
scar-4.3.1.dist-info/RECORD
