Metadata-Version: 2.1
Name: scar
Version: 4.3.1
Summary: CLI for deploying serverless infrastructures on multiple cloud environments
Home-page: https://github.com/grycap/scar
Author: GRyCAP - Universitat Politecnica de Valencia
Author-email: products@grycap.upv.es
License: Apache 2.0
Platform: any
Classifier: Programming Language :: Python :: 3
Classifier: License :: OSI Approved :: Apache Software License
License-File: LICENSE
Requires-Dist: boto3
Requires-Dist: configparser
Requires-Dist: docker
Requires-Dist: packaging
Requires-Dist: pyyaml
Requires-Dist: requests
Requires-Dist: setuptools (>=40.8.0)
Requires-Dist: tabulate
Requires-Dist: urllib3
